hypermodern_python/__init__.py
hypermodern_python/console.py
hypermodern_python/wikipedia.py
hypermodern_tutorial-0.1.4.dist-info/entry_points.txt
hypermodern_tutorial-0.1.4.dist-info/LICENSE
hypermodern_tutorial-0.1.4.dist-info/WHEEL
hypermodern_tutorial-0.1.4.dist-info/METADATA
hypermodern_tutorial-0.1.4.dist-info/RECORD
