Metadata-Version: 2.1
Name: hypermodern-tutorial
Version: 0.1.4
Summary: The hypermodern Python project - walking through tutorial
License: MIT
Keywords: hypermodern
Author: mattyocode
Author-email: matthewoliver@live.co.uk
Requires-Python: >=3.7,<4.0
Classifier: License :: OSI Approved :: MIT License
Classifier: Programming Language :: Python :: 3
Classifier: Programming Language :: Python :: 3.7
Classifier: Programming Language :: Python :: 3.8
Classifier: Programming Language :: Python :: 3.9
Requires-Dist: click (>=7.1.2,<8.0.0)
Requires-Dist: desert (>=2020.11.18,<2021.0.0)
Requires-Dist: importlib-metadata (>=3.3.0,<4.0.0); python_version < "3.8"
Requires-Dist: marshmallow (>=3.10.0,<4.0.0)
Requires-Dist: requests (>=2.24.0,<2.25.0)
Requires-Dist: typing-extensions (>=3.7.4,<4.0.0)
